thunkmetrc/__init__.py
thunkmetrc/wrapper/__init__.py
thunkmetrc/wrapper/ratelimiter.py
thunkmetrc/wrapper/wrapper.py
thunkmetrc_wrapper-0.2.2.dist-info/METADATA
thunkmetrc_wrapper-0.2.2.dist-info/WHEEL
thunkmetrc_wrapper-0.2.2.dist-info/RECORD
