Metadata-Version: 2.4
Name: thunkmetrc-wrapper
Version: 0.2.2
Summary: Type-safe wrapper for ThunkMetrc Python client
Author-email: ThunkMetrc <dev@thunkmetrc.com>
License-Expression: MIT
Requires-Python: >=3.10
Requires-Dist: thunkmetrc-client==0.2.2
